{
 "globalsettings":
 	{
 	"header": "Den Danske Magtelite",
 	"captures": {
 			"savetoSVG": false,
 			"savetoCanvas": true,
 			"embedSigma": true
 			},
 	"logo": "",
 	"url": ""
 	},
"graph1":
	{
	"graph_header": "Vælg datasæt",
	"basemap": "data/november_med_partier.gexf",
	"render": "webgl",
	"logo_url": "",
	"spatilize": false,
	"filter_by":[
				{"label": "Parti", "gephiCol": "parti", "keepNeighbors": true},
				{"label": "Name", "gephiCol": "label", "keepNeighbors": true}
				],
	"highlight_by":[
				{"label": "Parti", "gephiCol": "parti", "keepNeighbors": true, "multicolor": true},
				{"label": "Name", "gephiCol": "label", "keepNeighbors": true, "multicolor": false}
				],
	"merge_by":[
				{"label": "Merge by", "gephiCol": ["type", "from_user_timezone"]}
			   ],
	"compare_by":[
				{"label": "Color by", "gephiCol": ["parti", "type"]}
			   ],
	"color_by":[
				{"label": "Color by", "gephiCol": ["parti", "type"]}
			   ],
	"size_by":  [
				"original", "degree", "indegree", "outdegree"
				],
	"details_view":[
				{"label": "Parti", "gephiCol": "parti"},
				{"label": "connections", "gephiCol": "connections"},
				{"label": "Timezone", "gephiCol": "from_user_timezone"}
				]
	}
}
